{"leve": {"name": "大规模制作委托：赠与资助者的纪念品", "description": "有一位贵妇人对我神殿骑士团进行了很多资助。因为她是出了名的善于刺绣，我们想准备一套最高级的缝衣针赠与她作纪念。\n\n<UIForeground>F201F4</UIForeground><UIGlow>F201F5</UIGlow>要制作为完成本理符所需的物品，需要习得雕金秘籍第三卷。<UIGlow>01</UIGlow><UIForeground>01</UIForeground>", "id": 1146, "patch": "3.0", "level": 58, "jobCategory": 12, "complexity": {"nq": 30, "hq": 387}, "is_large": true, "repeat": 0}, "require": {"id": 11894, "name": "狮鹫缝针", "amount": 3}, "craft": [{"id": 31084, "job": 11, "rlvl": 150, "durability": 70, "quality": 7851, "progress": 956, "lvl": 60, "suggestedCraftsmanship": 587, "suggestedControl": 553, "materialQualityFactor": 50, "hq": 1, "quickSynth": 1, "unlockId": 12247, "ingredients": [{"id": 12577, "amount": 1, "quality": 996.524841, "name": "狮鹫钩爪"}, {"id": 12526, "amount": 1, "quality": 996.524841, "name": "精金块"}, {"id": 12583, "amount": 1, "quality": 996.524841, "name": "桦木木材"}, {"id": 12561, "amount": 1, "quality": 935.9254, "name": "白云母磨刀石"}, {"id": 16, "amount": 2, "name": "风之晶簇"}, {"id": 14, "amount": 1, "name": "火之晶簇"}], "complexity": {"nq": 109, "hq": 129}}], "ic": {"12526": [{"id": 2334, "job": 9, "rlvl": 145, "durability": 35, "quality": 7080, "progress": 431, "lvl": 58, "suggestedCraftsmanship": 570, "suggestedControl": 535, "materialQualityFactor": 50, "hq": 1, "quickSynth": 1, "ingredients": [{"id": 12538, "amount": 5, "quality": 659.01886, "name": "精金矿"}, {"id": 5121, "amount": 1, "quality": 244.905655, "name": "玄铁矿"}, {"id": 8, "amount": 5, "name": "火之水晶"}], "complexity": {"nq": 160, "hq": 180}}, {"id": 2406, "job": 10, "rlvl": 145, "durability": 35, "quality": 7080, "progress": 431, "lvl": 58, "suggestedCraftsmanship": 570, "suggestedControl": 535, "materialQualityFactor": 50, "hq": 1, "quickSynth": 1, "ingredients": [{"id": 12538, "amount": 5, "quality": 659.01886, "name": "精金矿"}, {"id": 5121, "amount": 1, "quality": 244.905655, "name": "玄铁矿"}, {"id": 9, "amount": 5, "name": "冰之水晶"}], "complexity": {"nq": 160, "hq": 180}}], "12583": [{"id": 2242, "job": 8, "rlvl": 145, "durability": 35, "quality": 7080, "progress": 431, "lvl": 58, "suggestedCraftsmanship": 570, "suggestedControl": 535, "materialQualityFactor": 50, "hq": 1, "quickSynth": 1, "ingredients": [{"id": 12579, "amount": 5, "quality": 708.0, "name": "桦木原木"}, {"id": 10, "amount": 5, "name": "风之水晶"}], "complexity": {"nq": 100, "hq": 120}}], "12561": [{"id": 2541, "job": 11, "rlvl": 139, "durability": 35, "quality": 6561, "progress": 376, "lvl": 56, "suggestedCraftsmanship": 550, "suggestedControl": 513, "materialQualityFactor": 50, "hq": 1, "quickSynth": 1, "ingredients": [{"id": 12539, "amount": 3, "quality": 1093.5, "name": "白云母"}, {"id": 10, "amount": 5, "name": "风之水晶"}], "complexity": {"nq": 55, "hq": 75}}]}, "reward": {"exp": 6294020, "gil": 5200, "items": [{"id": 10, "name": "风之水晶", "rate": 0.23, "amount": 30}, {"id": 8, "name": "火之水晶", "rate": 0.23, "amount": 30}, {"id": 12521, "name": "硬银锭", "rate": 0.23, "amount": 10}, {"id": 10, "name": "风之水晶", "rate": 0.1, "amount": 44}, {"id": 8, "name": "火之水晶", "rate": 0.1, "amount": 44}, {"id": 12533, "name": "皇金沙", "rate": 0.1, "amount": 40}]}}