{"leve": {"name": "批发委托：流镝马专用的弓", "description": "最近这里要举办一项活动，是由黄金港奉行主办的在马上用弓箭射击的流镝马。我们希望有人能帮忙制作活动中需要用到的榉木制弓。为了让所有参加者都能人手一把，我们想找一位老练的工匠进行大量的制作。", "id": 1252, "patch": "4.0", "level": 68, "jobCategory": 9, "complexity": {"nq": 20, "hq": 115}, "is_large": false, "repeat": 2}, "require": {"id": 18661, "name": "榉木长弓", "amount": 1}, "craft": [{"id": 3272, "job": 8, "rlvl": 285, "durability": 80, "quality": 11121, "progress": 2029, "lvl": 68, "suggestedCraftsmanship": 1069, "suggestedControl": 1043, "materialQualityFactor": 50, "hq": 1, "quickSynth": 1, "ingredients": [{"id": 19928, "amount": 3, "quality": 1121.54456, "name": "榉木木材"}, {"id": 19983, "amount": 1, "quality": 1097.93311, "name": "草原哔叽"}, {"id": 19984, "amount": 1, "quality": 1097.93311, "name": "精纺毛纱"}, {"id": 10, "amount": 5, "name": "风之水晶"}, {"id": 9, "amount": 5, "name": "冰之水晶"}], "complexity": {"nq": 95, "hq": 115}}], "ic": {"19928": [{"id": 3612, "job": 8, "rlvl": 285, "durability": 40, "quality": 11121, "progress": 1014, "lvl": 68, "suggestedCraftsmanship": 1069, "suggestedControl": 1043, "materialQualityFactor": 50, "hq": 1, "quickSynth": 1, "ingredients": [{"id": 19933, "amount": 4, "quality": 1390.125, "name": "榉木原木"}, {"id": 10, "amount": 5, "name": "风之水晶"}], "complexity": {"nq": 88, "hq": 108}}], "19983": [{"id": 3640, "job": 13, "rlvl": 279, "durability": 40, "quality": 10389, "progress": 904, "lvl": 66, "suggestedCraftsmanship": 1056, "suggestedControl": 1028, "materialQualityFactor": 50, "hq": 1, "quickSynth": 1, "ingredients": [{"id": 19984, "amount": 3, "quality": 1731.5, "name": "精纺毛纱"}, {"id": 12, "amount": 3, "name": "雷之水晶"}], "complexity": {"nq": 43, "hq": 63}}], "19984": [{"id": 3641, "job": 13, "rlvl": 279, "durability": 40, "quality": 10389, "progress": 904, "lvl": 66, "suggestedCraftsmanship": 1056, "suggestedControl": 1028, "materialQualityFactor": 50, "yield": 3, "hq": 1, "quickSynth": 1, "ingredients": [{"id": 19985, "amount": 2, "quality": 1283.67188, "name": "刺草鬃毛"}, {"id": 19986, "amount": 2, "quality": 1283.67188, "name": "曼殊师里的毛发"}, {"id": 5522, "amount": 1, "quality": 59.8126678, "name": "泡碱"}, {"id": 12, "amount": 2, "name": "雷之水晶"}], "complexity": {"nq": 128, "hq": 148}}], "5522": [{"id": 1141, "job": 14, "rlvl": 25, "durability": 40, "quality": 1296, "progress": 44, "lvl": 25, "suggestedCraftsmanship": 99, "suggestedControl": 49, "materialQualityFactor": 50, "hq": 1, "quickSynth": 1, "ingredients": [{"id": 5491, "amount": 1, "quality": 594.0, "name": "发泡水"}, {"id": 5518, "amount": 1, "quality": 54.0, "name": "岩盐"}, {"id": 7, "amount": 2, "name": "水之碎晶"}], "complexity": {"nq": 39, "hq": 59}}]}, "reward": {"exp": 2170110, "gil": 2912, "items": [{"id": 10, "name": "风之水晶", "rate": 0.23, "amount": 75}, {"id": 9, "name": "冰之水晶", "rate": 0.23, "amount": 75}, {"id": 19928, "name": "榉木木材", "rate": 0.23, "amount": 2}, {"id": 10, "name": "风之水晶", "rate": 0.1, "amount": 96}, {"id": 9, "name": "冰之水晶", "rate": 0.1, "amount": 96}, {"id": 19928, "name": "榉木木材", "rate": 0.1, "amount": 4}]}}