{"leve": {"name": "制作委托：打磨放大镜的幻水", "description": "此次想要委托调配的是巧力之幻水。巧力之幻水是用来打磨放大镜的，在不允许半点失误的手术中需要用到放大镜。如果稍有不慎，将奇怪的地方缝合了的话，那可就真的是一桩惨事了，所以拜托了。", "id": 1482, "patch": "5.0", "level": 72, "jobCategory": 15, "complexity": {"nq": 318, "hq": 378}, "is_large": false, "repeat": 0}, "require": {"id": 27768, "name": "1级巧力之幻水", "amount": 3}, "craft": [{"id": 3859, "job": 14, "rlvl": 400, "durability": 40, "quality": 14062, "progress": 1674, "lvl": 73, "suggestedCraftsmanship": 1457, "suggestedControl": 1348, "materialQualityFactor": 75, "yield": 3, "hq": 1, "quickSynth": 1, "ingredients": [{"id": 27968, "amount": 1, "quality": 3101.91187, "name": "高地天然水"}, {"id": 27763, "amount": 1, "quality": 3024.364, "name": "阱蛇麻的叶子"}, {"id": 19912, "amount": 2, "quality": 2210.112, "name": "香荠"}, {"id": 13, "amount": 6, "name": "水之水晶"}], "complexity": {"nq": 106, "hq": 126}}], "ic": {}, "reward": {"exp": 1644860, "gil": 2556, "items": [{"id": 13, "name": "水之水晶", "rate": 0.23, "amount": 31}, {"id": 12, "name": "雷之水晶", "rate": 0.23, "amount": 31}, {"id": 27968, "name": "高地天然水", "rate": 0.23, "amount": 1}, {"id": 13, "name": "水之水晶", "rate": 0.1, "amount": 36}, {"id": 12, "name": "雷之水晶", "rate": 0.1, "amount": 36}, {"id": 27968, "name": "高地天然水", "rate": 0.1, "amount": 2}]}}