{"leve": {"name": "制作委托：实用的硬泥岩砥石", "description": "对于工匠来说，道具的保养是必不可少的。所以，我每次完成工作后都必定会用磨刀石打磨道具的利刃，使其保持锋利。所以为了能够顺利完成工作，就麻烦你制作实用的硬泥岩砥石了。", "id": 1508, "patch": "5.0", "level": 70, "jobCategory": 12, "complexity": {"nq": 82, "hq": 102}, "is_large": false, "repeat": 0}, "require": {"id": 27802, "name": "硬泥岩砥石", "amount": 1}, "craft": [{"id": 3838, "job": 11, "rlvl": 390, "durability": 40, "quality": 13086, "progress": 1574, "lvl": 71, "suggestedCraftsmanship": 1320, "suggestedControl": 1220, "materialQualityFactor": 75, "hq": 1, "quickSynth": 1, "ingredients": [{"id": 27801, "amount": 3, "quality": 3271.5, "name": "硬泥岩"}, {"id": 10, "amount": 6, "name": "风之水晶"}], "complexity": {"nq": 82, "hq": 102}}], "ic": {}, "reward": {"exp": 606130, "gil": 1600, "items": [{"id": 10, "name": "风之水晶", "rate": 0.23, "amount": 30}, {"id": 8, "name": "火之水晶", "rate": 0.23, "amount": 30}, {"id": 27801, "name": "硬泥岩", "rate": 0.23, "amount": 1}, {"id": 10, "name": "风之水晶", "rate": 0.1, "amount": 35}, {"id": 8, "name": "火之水晶", "rate": 0.1, "amount": 35}, {"id": 27801, "name": "硬泥岩", "rate": 0.1, "amount": 2}]}}