{"leve":{"name":"Sometimes the South Wins","description":"Every now and then, highborn knights will come together to remember the glory days of yore with reenactments of Ishgard's finest battles, two houses on each side. While the recreations are meant to be historical, the knights rarely forget their house rivalries and the victorious side appears to change each time. Roughhousing and friendly jabs are expected and thus quality armor is needed so that the knights save their intended armor for our Dravanian foes.","id":1012,"patch":3.0,"client":"Temple Knights Second Commander Ser Handeloup","lvl":54,"jobCategory":11,"levemete":1011209,"areaid":2300,"xp":1113060,"gil":780,"rewards":345,"plate":80041,"frame":80005,"areaicon":110089,"repeats":2,"requires":[{"item":10679}],"complexity":{"nq":15,"hq":196}},"rewards":{"id":345,"entries":[{"item":9,"rate":0.23,"amount":12},{"item":11,"rate":0.23,"amount":12},{"item":12519,"rate":0.23,"amount":2},{"item":9,"rate":0.05,"amount":18},{"item":11,"rate":0.05,"amount":18},{"item":12537,"rate":0.05,"amount":8},{"item":11880,"rate":0.05,"hq":1},{"item":11957,"rate":0.05,"hq":1},{"item":11967,"rate":0.05,"hq":1}]},"ingredients":[{"name":"Titanium Mail of Fending","id":10679,"icon":42882,"category":35,"ilvl":133,"price":24644,"craft":[{"id":2348,"job":10,"rlvl":136,"durability":70,"quality":6301,"progress":697,"lvl":55,"suggestedCraftsmanship":539,"suggestedControl":502,"materialQualityFactor":50,"hq":1,"quickSynth":1,"ingredients":[{"id":12524,"amount":2,"quality":582.949646},{"id":12564,"amount":1,"quality":582.949646},{"id":12590,"amount":2,"quality":582.949646},{"id":5068,"amount":1,"quality":235.7517},{"id":9,"amount":4},{"id":11,"amount":4}],"complexity":{"nq":176,"hq":196}}],"leves":[890,891,892,893,894,895],"vendors":[1012073,1012086,1011204]},{"name":"Titanium Nugget","id":12524,"icon":20829,"category":49,"ilvl":136,"price":2692,"craft":[{"id":2332,"job":9,"rlvl":133,"durability":40,"quality":6042,"progress":320,"lvl":54,"suggestedCraftsmanship":529,"suggestedControl":491,"materialQualityFactor":50,"hq":1,"quickSynth":1,"ingredients":[{"id":12537,"amount":5,"quality":560.512939},{"id":5111,"amount":1,"quality":53.5784454},{"id":5526,"amount":1,"quality":164.85675},{"id":8,"amount":4}],"complexity":{"nq":104,"hq":124}},{"id":2404,"job":10,"rlvl":133,"durability":40,"quality":6042,"progress":320,"lvl":54,"suggestedCraftsmanship":529,"suggestedControl":491,"materialQualityFactor":50,"hq":1,"quickSynth":1,"ingredients":[{"id":12537,"amount":5,"quality":560.512939},{"id":5111,"amount":1,"quality":53.5784454},{"id":5526,"amount":1,"quality":164.85675},{"id":9,"amount":4}],"complexity":{"nq":104,"hq":124}}],"tradeShops":[{"shop":"Steel Spoils Exchange (DoL) II","npcs":[],"listings":[{"item":[{"id":"12524","amount":6}],"currency":[{"id":"13631","amount":1}]}]},{"shop":"Black Copper Gil Exchange","npcs":[1016804],"listings":[{"item":[{"id":"12524","amount":1}],"currency":[{"id":"21079","amount":1}]}]},{"shop":"Curious Crop Exchange","npcs":[1005633,1005640,1005647,1018091,1018094,1018097,1019101,1019111],"listings":[{"item":[{"id":"12524","amount":3}],"currency":[{"id":"15857","amount":1}]}]},{"shop":"Sky Pirate Spoils (Steel)","npcs":[1016261,1016496,1016498,1016500,1019106],"listings":[{"item":[{"id":"12524","amount":6}],"currency":[{"id":"13631","amount":1}]}]}],"leves":[986,987,988,989,990,991,1016,1017,1018,1019,1020,1021],"vendors":[1016804,1017188]},{"name":"Titanium Ore","id":12537,"icon":21222,"category":48,"ilvl":136,"price":807,"leves":[980,981,982,983,984,985,1010,1011,1012,1013,1014,1015],"ventures":[546],"nodes":[286]},{"name":"Iron Ore","id":5111,"icon":21202,"category":48,"ilvl":13,"price":18,"leves":[159,160,161,162,163,164,165,166,167,168,169,170,219,220,221,222,223,224,225,226,227,228,229,230],"ventures":[89],"drops":[21270000001671,1890000001836,16240000001598,13950000000629,23390000002275,1880000000275,1880000002008,19130000002005,1870000000278,36840000003350],"nodes":[158],"vendors":[1000999,1008837,1008838,1008839,1008840,1008841,1008842,1008843,1008844,1008845,1008846,1013117,1013118,1018662,1018663,1018664,1018665,1018666,1018667,1018668,1018669,1018670,1018671,1018672,1018673,1024548,1024549,1024550,1024551,1024552,1024553,1024554,1024555,1024556,1024557,1024558,1024559,1025039,1025043,1027015,1025717,1026169]},{"name":"Grenade Ash","id":5526,"icon":21001,"category":54,"ilvl":40,"price":216,"ventures":[56,146],"drops":[16180000001799,20920000000270,21380000001511,3270000000270],"nodes":[20],"vendors":[1001015]},{"name":"Dhalmel Leather","id":12564,"icon":22013,"category":52,"ilvl":136,"price":3402,"craft":[{"id":2655,"job":12,"rlvl":133,"durability":40,"quality":6042,"progress":320,"lvl":54,"suggestedCraftsmanship":529,"suggestedControl":491,"materialQualityFactor":50,"hq":1,"quickSynth":1,"ingredients":[{"id":12570,"amount":3,"quality":755.25},{"id":12578,"amount":1,"quality":755.25},{"id":11,"amount":4}],"complexity":{"nq":118,"hq":138}}],"tradeShops":[{"shop":"Brass Spoils Exchange (Materials/Gear)","npcs":[],"listings":[{"item":[{"id":"12564","amount":8}],"currency":[{"id":"13630","amount":1}]}]},{"shop":"Sky Pirate Spoils (Brass)","npcs":[1016261,1016496,1016498,1016500,1019106],"listings":[{"item":[{"id":"12564","amount":8}],"currency":[{"id":"13630","amount":1}]}]}],"leves":[956,957,958,959,960,961],"vendors":[1017188]},{"name":"Dhalmel Hide","id":12570,"icon":21806,"category":52,"ilvl":136,"price":1184,"leves":[950,951,952,953,954,955],"ventures":[428],"drops":[40690000003505]},{"name":"Dark Chestnut Log","id":12578,"icon":22420,"category":50,"ilvl":136,"price":753,"leves":[920,921,922,923,924,925],"ventures":[468],"nodes":[295]},{"name":"Ramie Cloth","id":12590,"icon":21605,"category":51,"ilvl":136,"price":3618,"craft":[{"id":2753,"job":13,"rlvl":133,"durability":40,"quality":6042,"progress":320,"lvl":54,"suggestedCraftsmanship":529,"suggestedControl":491,"materialQualityFactor":50,"hq":1,"quickSynth":1,"ingredients":[{"id":12595,"amount":2,"quality":1351.5},{"id":5336,"amount":1,"quality":318.0},{"id":12,"amount":2}],"complexity":{"nq":37,"hq":57}}],"tradeShops":[{"shop":"Steel Spoils Exchange (DoL) II","npcs":[],"listings":[{"item":[{"id":"12590","amount":6}],"currency":[{"id":"13631","amount":1}]}]},{"shop":"Sky Pirate Spoils (Steel)","npcs":[1016261,1016496,1016498,1016500,1019106],"listings":[{"item":[{"id":"12590","amount":6}],"currency":[{"id":"13631","amount":1}]}]}],"leves":[1100,1101,1102,1103,1104,1105],"vendors":[1017188]},{"name":"Ramie Thread","id":12595,"icon":21659,"category":51,"ilvl":136,"price":1998,"craft":[{"id":2757,"job":13,"rlvl":133,"durability":40,"quality":6042,"progress":320,"lvl":54,"suggestedCraftsmanship":529,"suggestedControl":491,"materialQualityFactor":50,"yield":2,"hq":1,"quickSynth":1,"ingredients":[{"id":12598,"amount":3,"quality":870.457642},{"id":5346,"amount":2,"quality":204.813553},{"id":12,"amount":2}],"complexity":{"nq":82,"hq":102}}],"leves":[1100,1101,1102,1103,1104,1105],"vendors":[1017188]},{"name":"Stalk of Ramie","id":12598,"icon":21651,"category":51,"ilvl":136,"price":484,"ventures":[467],"nodes":[297]},{"name":"Flax","id":5346,"icon":21651,"category":51,"ilvl":32,"price":83,"leves":[417,418,419,420,421,422,423,424,425,426,427,428],"ventures":[266],"nodes":[29],"seeds":[7741]},{"name":"Linen Yarn","id":5336,"icon":21659,"category":51,"ilvl":32,"price":186,"craft":[{"id":587,"job":13,"rlvl":32,"durability":40,"quality":1697,"progress":55,"lvl":32,"suggestedCraftsmanship":121,"suggestedControl":60,"materialQualityFactor":50,"yield":2,"hq":1,"quickSynth":1,"ingredients":[{"id":5346,"amount":2,"quality":424.25},{"id":6,"amount":2}],"complexity":{"nq":46,"hq":66}}],"tradeShops":[{"shop":"Sylphic Goldleaf Exchange","npcs":[1005569],"listings":[{"item":[{"id":"5336","amount":3}],"currency":[{"id":"21075","amount":1}]}]}],"vendors":[1005569]},{"name":"Rose Gold Nugget","id":5068,"icon":20821,"category":49,"ilvl":55,"price":1089,"craft":[{"id":1471,"job":11,"rlvl":55,"durability":40,"quality":2646,"progress":97,"lvl":50,"suggestedCraftsmanship":325,"suggestedControl":325,"materialQualityFactor":50,"stars":1,"hq":1,"quickSynth":1,"craftsmanshipReq":275,"quickSynthCraftsmanship":347,"ingredients":[{"id":5118,"amount":3,"quality":438.343384},{"id":5106,"amount":1,"quality":7.96987963},{"id":10,"amount":3}],"complexity":{"nq":93,"hq":113}}]},{"name":"Gold Ore","id":5118,"icon":21212,"category":48,"ilvl":55,"price":326,"voyages":["Sea of Clouds 02","Sea of Clouds 08","Sea of Clouds 14","Sea of Clouds 20","The Wreckage of the Headway"],"tradeShops":[{"shop":"Curious Crop Exchange","npcs":[1005633,1005640,1005647,1018091,1018094,1018097,1019101,1019111],"listings":[{"item":[{"id":"5118","amount":3}],"currency":[{"id":"15858","amount":1}]}]}],"ventures":[509],"nodes":[223]},{"name":"Copper Ore","id":5106,"icon":21209,"category":48,"ilvl":1,"price":2,"leves":[147,148,149,150,151,152,153,154,155,156,157,158,207,208,209,210,211,212,213,214,215,216,217,218,441,442,443,444,445,446,447,448,449,450,451,452],"ventures":[69],"nodes":[153,154],"vendors":[1000996,1000999,1004419,1000236,1001204,1001966,1008837,1008838,1008839,1008840,1008841,1008842,1008843,1008844,1008845,1008846,1013117,1013118,1018662,1018663,1018664,1018665,1018666,1018667,1018668,1018669,1018670,1018671,1018672,1018673,1024548,1024549,1024550,1024551,1024552,1024553,1024554,1024555,1024556,1024557,1024558,1024559,1025039,1025043,1027015,1011201,1025717,1026169]}],"partials":[{"type":"npc","id":"1016804","obj":{"i":1016804,"n":"Vath Stickpeddler","l":2000,"s":2,"r":1,"a":2021,"c":[23.68,19.1]}},{"type":"npc","id":"1017188","obj":{"i":1017188,"n":"Scrap Salvager","l":2082,"s":3,"c":["5.9","7.3"]}},{"type":"item","id":"13631","obj":{"i":13631,"n":"Steel Sky Pirate Spoil","l":1,"c":25951,"t":61}},{"type":"item","id":"21079","obj":{"i":21079,"n":"Black Copper Gil","l":1,"c":65056,"t":63}},{"type":"npc","id":"1005633","obj":{"i":1005633,"n":"Material Supplier","l":425,"s":3,"r":1,"a":1202,"c":[11.04,11.4]}},{"type":"npc","id":"1005640","obj":{"i":1005640,"n":"Material Supplier","l":427,"s":3,"r":1,"a":1115,"c":[10.97,8.96]}},{"type":"npc","id":"1005647","obj":{"i":1005647,"n":"Material Supplier","l":426,"s":3,"r":1,"a":1146,"c":[11.94,8.33]}},{"type":"npc","id":"1018091","obj":{"i":1018091,"n":"Apartment Merchant","l":1813,"s":8,"r":1,"a":1146,"c":[6.15,6.03]}},{"type":"npc","id":"1018094","obj":{"i":1018094,"n":"Apartment Merchant","l":1811,"s":8,"r":1,"a":1146,"c":[6.15,6.03]}},{"type":"npc","id":"1018097","obj":{"i":1018097,"n":"Apartment Merchant","l":1815,"s":8,"r":1,"a":1146,"c":[6.15,6.03]}},{"type":"npc","id":"1019101","obj":{"i":1019101,"n":"Material Supplier","l":2412,"s":3,"r":1,"c":["10.5","12.2"]}},{"type":"npc","id":"1019111","obj":{"i":1019111,"n":"Apartment Merchant","l":2272,"s":8,"r":1,"c":["6.1","6.0"]}},{"type":"item","id":"15857","obj":{"i":15857,"n":"Althyk Lavender","l":155,"c":25002,"t":54}},{"type":"npc","id":"1016261","obj":{"i":1016261,"n":"Spoils Collector","l":2301,"s":3,"r":1,"a":2323,"c":[14.75,11.0]}},{"type":"npc","id":"1016496","obj":{"i":1016496,"n":"Spoils Collector","l":426,"s":3,"r":1,"a":1222,"c":[11.23,15.11]}},{"type":"npc","id":"1016498","obj":{"i":1016498,"n":"Spoils Collector","l":425,"s":3,"r":1,"a":1200,"c":[10.93,8.99]}},{"type":"npc","id":"1016500","obj":{"i":1016500,"n":"Spoils Collector","l":427,"s":3,"r":1,"a":1152,"c":[11.77,7.4]}},{"type":"npc","id":"1019106","obj":{"i":1019106,"n":"Spoils Collector","l":2412,"s":3,"r":1,"a":1912,"c":[9.13,9.26]}},{"type":"item","id":"12537","obj":{"i":12537,"n":"Titanium Ore","l":136,"c":21222,"t":48}},{"type":"item","id":"5111","obj":{"i":5111,"n":"Iron Ore","l":13,"c":21202,"t":48,"p":18}},{"type":"item","id":"5526","obj":{"i":5526,"n":"Grenade Ash","l":40,"c":21001,"t":54,"p":216}},{"type":"node","id":"286","obj":{"i":286,"n":"Chocobo Forest","l":55,"t":0,"z":2000}},{"type":"node","id":"158","obj":{"i":158,"n":"Horizon's Edge","l":15,"t":0,"z":42}},{"type":"npc","id":"1000999","obj":{"i":1000999,"n":"Soemrwyb","l":28,"s":1,"t":"Guild Supplier","c":["10.6","15.1"]}},{"type":"npc","id":"1008837","obj":{"i":1008837,"n":"Material Supplier","s":3}},{"type":"npc","id":"1008838","obj":{"i":1008838,"n":"Material Supplier","s":3}},{"type":"npc","id":"1008839","obj":{"i":1008839,"n":"Material Supplier","s":3}},{"type":"npc","id":"1008840","obj":{"i":1008840,"n":"Material Supplier","s":3}},{"type":"npc","id":"1008841","obj":{"i":1008841,"n":"Material Supplier","s":3}},{"type":"npc","id":"1008842","obj":{"i":1008842,"n":"Material Supplier","s":3}},{"type":"npc","id":"1008843","obj":{"i":1008843,"n":"Material Supplier","s":3}},{"type":"npc","id":"1008844","obj":{"i":1008844,"n":"Material Supplier","s":3}},{"type":"npc","id":"1008845","obj":{"i":1008845,"n":"Material Supplier","s":3}},{"type":"npc","id":"1008846","obj":{"i":1008846,"n":"Material Supplier","s":3}},{"type":"npc","id":"1013117","obj":{"i":1013117,"n":"Material Supplier","s":3}},{"type":"npc","id":"1013118","obj":{"i":1013118,"n":"Material Supplier","s":3}},{"type":"npc","id":"1018662","obj":{"i":1018662,"n":"Material Supplier","s":3}},{"type":"npc","id":"1018663","obj":{"i":1018663,"n":"Material Supplier","s":3}},{"type":"npc","id":"1018664","obj":{"i":1018664,"n":"Material Supplier","s":3}},{"type":"npc","id":"1018665","obj":{"i":1018665,"n":"Material Supplier","s":3}},{"type":"npc","id":"1018666","obj":{"i":1018666,"n":"Material Supplier","s":3}},{"type":"npc","id":"1018667","obj":{"i":1018667,"n":"Material Supplier","s":3}},{"type":"npc","id":"1018668","obj":{"i":1018668,"n":"Material Supplier","s":3}},{"type":"npc","id":"1018669","obj":{"i":1018669,"n":"Material Supplier","s":3}},{"type":"npc","id":"1018670","obj":{"i":1018670,"n":"Material Supplier","s":3}},{"type":"npc","id":"1018671","obj":{"i":1018671,"n":"Material Supplier","s":3}},{"type":"npc","id":"1018672","obj":{"i":1018672,"n":"Material Supplier","s":3}},{"type":"npc","id":"1018673","obj":{"i":1018673,"n":"Material Supplier","s":3}},{"type":"npc","id":"1024548","obj":{"i":1024548,"n":"Material Supplier","s":3}},{"type":"npc","id":"1024549","obj":{"i":1024549,"n":"Material Supplier","s":3}},{"type":"npc","id":"1024550","obj":{"i":1024550,"n":"Material Supplier","s":3}},{"type":"npc","id":"1024551","obj":{"i":1024551,"n":"Material Supplier","s":3}},{"type":"npc","id":"1024552","obj":{"i":1024552,"n":"Material Supplier","s":3}},{"type":"npc","id":"1024553","obj":{"i":1024553,"n":"Material Supplier","s":3}},{"type":"npc","id":"1024554","obj":{"i":1024554,"n":"Material Supplier","s":3}},{"type":"npc","id":"1024555","obj":{"i":1024555,"n":"Material Supplier","s":3}},{"type":"npc","id":"1024556","obj":{"i":1024556,"n":"Material Supplier","s":3}},{"type":"npc","id":"1024557","obj":{"i":1024557,"n":"Material Supplier","s":3}},{"type":"npc","id":"1024558","obj":{"i":1024558,"n":"Material Supplier","s":3}},{"type":"npc","id":"1024559","obj":{"i":1024559,"n":"Material Supplier","s":3}},{"type":"npc","id":"1025039","obj":{"i":1025039,"n":"Allagan Resupply Node","s":3}},{"type":"npc","id":"1025043","obj":{"i":1025043,"n":"Ananta Material Supplier","s":3}},{"type":"npc","id":"1027015","obj":{"i":1027015,"n":"Kojin Material Supplier","s":3}},{"type":"npc","id":"1025717","obj":{"i":1025717,"n":"Namazu Material Supplier","s":3}},{"type":"npc","id":"1026169","obj":{"i":1026169,"n":"Namazu Material Supplier","s":3}},{"type":"mob","id":"1880000000275","obj":{"i":1880000000275,"n":"Quartz Doblyn","l":"49","z":46}},{"type":"mob","id":"1870000000278","obj":{"i":1870000000278,"n":"Lead Coblyn","l":"21","z":42}},{"type":"mob","id":"13950000000629","obj":{"i":13950000000629,"n":"Copperbell Coblyn","l":"17","z":48}},{"type":"mob","id":"16240000001598","obj":{"i":16240000001598,"n":"Schorl Doblyn","l":"38","z":47}},{"type":"mob","id":"21270000001671","obj":{"i":21270000001671,"n":"Asbestos Coblyn","l":"48","z":350}},{"type":"mob","id":"1890000001836","obj":{"i":1890000001836,"n":"Synthetic Doblyn","l":"48 - 49","z":350}},{"type":"mob","id":"19130000002005","obj":{"i":19130000002005,"n":"Ceruleum Coblyn","l":"38","z":46}},{"type":"mob","id":"1880000002008","obj":{"i":1880000002008,"n":"Sphene Doblyn","l":"49","z":46}},{"type":"mob","id":"23390000002275","obj":{"i":23390000002275,"n":"Chalcopyrite Coblyn","l":"50","z":48}},{"type":"mob","id":"36840000003350","obj":{"i":36840000003350,"n":"Cermet Coblyn","l":"50","z":418}},{"type":"node","id":"20","obj":{"i":20,"n":"Bluefog","l":40,"t":1,"z":46}},{"type":"npc","id":"1001015","obj":{"i":1001015,"n":"Z'ranmaia","l":28,"s":1,"t":"Herbalist","a":718,"c":[11.35,8.16]}},{"type":"mob","id":"3270000000270","obj":{"i":3270000000270,"n":"Grenade","l":"41 - 44","z":350}},{"type":"mob","id":"20920000000270","obj":{"i":20920000000270,"n":"Grenade","l":"49","z":46}},{"type":"mob","id":"21380000001511","obj":{"i":21380000001511,"n":"Bomb Baron","l":"49","z":46}},{"type":"mob","id":"16180000001799","obj":{"i":16180000001799,"n":"Shrapnel","l":"38","z":47}},{"type":"item","id":"13630","obj":{"i":13630,"n":"Brass Sky Pirate Spoil","l":1,"c":25950,"t":61}},{"type":"item","id":"12570","obj":{"i":12570,"n":"Dhalmel Hide","l":136,"c":21806,"t":52}},{"type":"item","id":"12578","obj":{"i":12578,"n":"Dark Chestnut Log","l":136,"c":22420,"t":50}},{"type":"mob","id":"40690000003505","obj":{"i":40690000003505,"n":"Dhalmel","l":"56","z":2100}},{"type":"node","id":"295","obj":{"i":295,"n":"The Smoldering Wastes","l":55,"t":2,"z":2000}},{"type":"item","id":"12595","obj":{"i":12595,"n":"Ramie Thread","l":136,"c":21659,"t":51,"p":1998}},{"type":"item","id":"5336","obj":{"i":5336,"n":"Linen Yarn","l":32,"c":21659,"t":51,"p":186}},{"type":"item","id":"12598","obj":{"i":12598,"n":"Stalk of Ramie","l":136,"c":21651,"t":51}},{"type":"item","id":"5346","obj":{"i":5346,"n":"Flax","l":32,"c":21651,"t":51}},{"type":"node","id":"297","obj":{"i":297,"n":"Chocobo Forest","l":55,"t":3,"z":2000}},{"type":"node","id":"29","obj":{"i":29,"n":"Lower Paths","l":35,"t":3,"z":56}},{"type":"npc","id":"1005569","obj":{"i":1005569,"n":"Sylphic Vendor","l":55,"s":2,"r":1,"a":113,"c":[22.37,26.4]}},{"type":"item","id":"21075","obj":{"i":21075,"n":"Sylphic Goldleaf","l":1,"c":65051,"t":63}},{"type":"item","id":"5118","obj":{"i":5118,"n":"Gold Ore","l":55,"c":21212,"t":48}},{"type":"item","id":"5106","obj":{"i":5106,"n":"Copper Ore","l":1,"c":21209,"t":48,"p":2}},{"type":"node","id":"223","obj":{"i":223,"n":"The Burning Wall","l":50,"t":0,"z":44,"s":1,"lt":"Unspoiled","ti":[9]}},{"type":"item","id":"15858","obj":{"i":15858,"n":"Voidrake","l":155,"c":25004,"t":54}},{"type":"node","id":"153","obj":{"i":153,"n":"Spineless Basin","l":5,"t":0,"z":43}},{"type":"node","id":"154","obj":{"i":154,"n":"Hammerlea","l":5,"t":0,"z":42}},{"type":"npc","id":"1000996","obj":{"i":1000996,"n":"Smydhaemr","l":28,"s":1,"t":"Guild Supplier","c":["10.6","15.1"]}},{"type":"npc","id":"1004419","obj":{"i":1004419,"n":"Aistan","l":41,"s":1,"t":"Guild Supplier","c":["10.5","13.1"]}},{"type":"npc","id":"1000236","obj":{"i":1000236,"n":"O'rhoyod","l":53,"s":1,"t":"Tradecraft Supplier","a":564,"c":[14.42,8.96]}},{"type":"npc","id":"1001204","obj":{"i":1001204,"n":"Engerrand","l":29,"s":1,"q":1,"t":"Tradecraft Supplier","a":744,"c":[8.66,11.82]}},{"type":"npc","id":"1001966","obj":{"i":1001966,"n":"Fridurih","l":41,"s":1,"q":1,"t":"Tradecraft Merchant","a":646,"c":[13.79,9.57]}},{"type":"npc","id":"1011201","obj":{"i":1011201,"n":"Pasdevillet","l":2301,"s":1,"t":"Sundries Vendor","a":2317,"c":[7.33,10.71]}},{"type":"item","id":"9037","obj":{"i":9037,"n":"Wootz Mail","l":110,"c":42869,"t":35}},{"type":"npc","id":"1012073","obj":{"i":1012073,"n":"Emptier Of Purses","l":2002,"s":6,"a":2042,"c":[28.44,34.21]}},{"type":"npc","id":"1012086","obj":{"i":1012086,"n":"Moogle Mender & Merchant","l":2002,"s":5,"a":2045,"c":[20.67,26.37]}},{"type":"npc","id":"1011204","obj":{"i":1011204,"n":"Norlaise","l":2301,"s":19,"q":1,"t":"Armorer","a":2317,"c":[7.17,10.18]}},{"type":"item","id":"12524","obj":{"i":12524,"n":"Titanium Nugget","l":136,"c":20829,"t":49,"p":2692}},{"type":"item","id":"12564","obj":{"i":12564,"n":"Dhalmel Leather","l":136,"c":22013,"t":52,"p":3402}},{"type":"item","id":"12590","obj":{"i":12590,"n":"Ramie Cloth","l":136,"c":21605,"t":51,"p":3618}},{"type":"item","id":"5068","obj":{"i":5068,"n":"Rose Gold Nugget","l":55,"c":20821,"t":49}},{"type":"quest","id":"67161","obj":{"i":67161,"n":"The Road to Zenith","g":3,"l":"The Churning Mists","s":46}},{"type":"leve","id":"890","obj":{"i":890,"n":"Show Your Work","l":54,"j":34,"p":2042}},{"type":"leve","id":"891","obj":{"i":891,"n":"Puppet Show","l":54,"j":34,"p":2042}},{"type":"leve","id":"892","obj":{"i":892,"n":"Cry Home","l":54,"j":34,"p":2042}},{"type":"leve","id":"893","obj":{"i":893,"n":"Family Comes First (L)","l":54,"j":34,"p":2042}},{"type":"leve","id":"894","obj":{"i":894,"n":"More Than One Way (L)","l":54,"j":34,"p":2042}},{"type":"leve","id":"895","obj":{"i":895,"n":"Hello, Cousin (L)","l":54,"j":34,"p":2042}},{"type":"leve","id":"1012","obj":{"i":1012,"n":"Sometimes the South Wins","l":54,"j":11,"p":2300}},{"type":"leve","id":"1015","obj":{"i":1015,"n":"The Thriller of Autumn (L)","l":54,"j":11,"p":2300}},{"type":"item","id":"10678","obj":{"i":10678,"n":"Holy Rainbow Shirt of Fending","l":125,"c":43265,"t":35,"p":15444}},{"type":"item","id":"10680","obj":{"i":10680,"n":"Titanium Cuirass of Fending","l":139,"c":42884,"t":35,"p":30051}},{"type":"npc","id":"1011209","obj":{"i":1011209,"n":"Fionnuala","l":2300}},{"type":"item","id":"12519","obj":{"i":12519,"n":"Mythrite Ingot","l":130,"c":20824,"t":49,"p":2652}},{"type":"item","id":"11880","obj":{"i":11880,"n":"Titanium Ball-pein Hammer","l":100,"c":35218,"t":16,"p":15206}},{"type":"item","id":"11957","obj":{"i":11957,"n":"Ramie Turban of Crafting","l":100,"c":41270,"t":34,"p":9979}},{"type":"item","id":"11967","obj":{"i":11967,"n":"Dhalmelskin Halfgloves of Crafting","l":100,"c":44391,"t":37,"p":11088}},{"type":"item","id":"10679","obj":{"i":10679,"n":"Titanium Mail of Fending","l":133,"c":42882,"t":35,"p":24644}}]}