{"leve":{"name":"Through a Glass Brightly","description":"The First Dicasterial Observatorium of Aetherial and Astrological Phenomena has taken delivery of a new lens, and the stargazers are all as giddy as a bridegroom over the fine, cloudless glass. However, they are martyrs to frozen hands, nights being their preferred gazing time. Fingerless gloves will keep them unencumbered whilst alleviating suffering.","id":127,"patch":2.0,"client":"Independent Sutler, Vivenne Pamisolaux","lvl":35,"jobCategory":13,"levemete":1002385,"areaid":385,"xp":173660,"gil":551,"rewards":117,"plate":80033,"frame":80005,"areaicon":110062,"requires":[{"item":3625}],"complexity":{"nq":5,"hq":293}},"rewards":{"id":117,"entries":[{"item":5,"rate":0.27,"amount":32},{"item":4,"rate":0.27,"amount":32},{"item":5303,"rate":0.27,"amount":13},{"item":5,"rate":0.04,"amount":52},{"item":4,"rate":0.04,"amount":52},{"item":3964,"rate":0.04},{"item":3602,"rate":0.04},{"item":3830,"rate":0.04}]},"ingredients":[{"name":"Fingerless Peisteskin Gloves","id":3625,"icon":44102,"category":37,"ilvl":40,"price":3780,"craft":[{"id":424,"job":12,"rlvl":38,"durability":80,"quality":1961,"progress":129,"lvl":38,"suggestedCraftsmanship":129,"suggestedControl":64,"materialQualityFactor":50,"hq":1,"quickSynth":1,"ingredients":[{"id":5284,"amount":2,"quality":273.963226},{"id":5282,"amount":1,"quality":237.915436},{"id":5093,"amount":1,"quality":194.658081},{"id":5,"amount":4},{"id":4,"amount":4}],"complexity":{"nq":273,"hq":293}}],"leves":[643,644,645,646,647,648,649,650,651,652,653,654,655],"vendors":[1006800,1000215,1001203,1001965,1011204]},{"name":"Peiste Leather","id":5284,"icon":22024,"category":52,"ilvl":38,"price":557,"craft":[{"id":421,"job":12,"rlvl":38,"durability":40,"quality":1961,"progress":64,"lvl":38,"suggestedCraftsmanship":129,"suggestedControl":64,"materialQualityFactor":50,"hq":1,"quickSynth":1,"ingredients":[{"id":5306,"amount":1,"quality":496.786652},{"id":5525,"amount":1,"quality":483.713348},{"id":5,"amount":4}],"complexity":{"nq":70,"hq":90}}]},{"name":"Peiste Skin","id":5306,"icon":21822,"category":52,"ilvl":38,"price":272,"leves":[129,130,131,132,133,134],"ventures":[52],"drops":[10470000001293,16170000001593,28200000002586,1730000000304,1740000000303,21880000001993]},{"name":"Black Alumen","id":5525,"icon":22604,"category":54,"ilvl":37,"price":189,"ventures":[145],"nodes":[49]},{"name":"Boar Leather","id":5282,"icon":22015,"category":52,"ilvl":33,"price":441,"craft":[{"id":406,"job":12,"rlvl":33,"durability":40,"quality":1757,"progress":55,"lvl":33,"suggestedCraftsmanship":121,"suggestedControl":60,"materialQualityFactor":50,"hq":1,"quickSynth":1,"ingredients":[{"id":5303,"amount":1,"quality":579.81},{"id":5524,"amount":1,"quality":298.69},{"id":5,"amount":4}],"complexity":{"nq":70,"hq":90}}]},{"name":"Boar Hide","id":5303,"icon":21816,"category":52,"ilvl":33,"price":215,"leves":[117,118,119,120,121,122,123,124,125,126,127,128],"ventures":[51],"drops":[21230000001667,160000000015,18860000001975,31180000000015,150000000016]},{"name":"Alumen","id":5524,"icon":22616,"category":54,"ilvl":17,"price":28,"ventures":[98],"nodes":[160]},{"name":"Steel Rivets","id":5093,"icon":21003,"category":49,"ilvl":27,"price":313,"craft":[{"id":98,"job":9,"rlvl":29,"durability":40,"quality":1544,"progress":50,"lvl":29,"suggestedCraftsmanship":106,"suggestedControl":53,"materialQualityFactor":50,"hq":1,"quickSynth":1,"ingredients":[{"id":5058,"amount":1,"quality":772.0},{"id":2,"amount":3}],"complexity":{"nq":33,"hq":53}},{"id":228,"job":10,"rlvl":27,"durability":40,"quality":1368,"progress":45,"lvl":27,"suggestedCraftsmanship":99,"suggestedControl":49,"materialQualityFactor":50,"hq":1,"quickSynth":1,"ingredients":[{"id":5058,"amount":1,"quality":684.0},{"id":3,"amount":3}],"complexity":{"nq":33,"hq":53}}],"tradeShops":[{"shop":"Steel Amalj'ok Exchange","npcs":[1005554],"listings":[{"item":[{"id":"5093","amount":3}],"currency":[{"id":"21076","amount":1}]}]}],"vendors":[1005554]},{"name":"Steel Ingot","id":5058,"icon":20802,"category":49,"ilvl":26,"price":258,"craft":[{"id":87,"job":9,"rlvl":26,"durability":40,"quality":1332,"progress":45,"lvl":26,"suggestedCraftsmanship":99,"suggestedControl":49,"materialQualityFactor":50,"hq":1,"quickSynth":1,"ingredients":[{"id":5528,"amount":1,"quality":333.0},{"id":5111,"amount":2,"quality":166.5},{"id":2,"amount":2}],"complexity":{"nq":37,"hq":57}},{"id":225,"job":10,"rlvl":26,"durability":40,"quality":1332,"progress":45,"lvl":26,"suggestedCraftsmanship":99,"suggestedControl":49,"materialQualityFactor":50,"hq":1,"quickSynth":1,"ingredients":[{"id":5528,"amount":1,"quality":333.0},{"id":5111,"amount":2,"quality":166.5},{"id":3,"amount":2}],"complexity":{"nq":37,"hq":57}}],"desynthedFrom":[9532,9533,9531],"tradeShops":[{"shop":"Steel Amalj'ok Exchange","npcs":[1005554],"listings":[{"item":[{"id":"5058","amount":3}],"currency":[{"id":"21076","amount":1}]}]}],"vendors":[1005554]},{"name":"Bomb Ash","id":5528,"icon":21001,"category":54,"ilvl":26,"price":82,"tradeShops":[{"shop":"Titan Cobaltpiece Exchange","npcs":[1008909],"listings":[{"item":[{"id":"5528","amount":3}],"currency":[{"id":"21078","amount":1}]}]}],"leves":[171,172,173,174,175,176,177,178,179,180,181,182,231,232,233,234,235,236,237,238,239,240,241,242],"ventures":[39,110],"drops":[170000002743,170000002707,170000002688,170000002745,170000000270,2570000000425,170000000017,22660000002189,23440000002280,14150000001193,170000000132],"nodes":[169],"vendors":[1008909]},{"name":"Iron Ore","id":5111,"icon":21202,"category":48,"ilvl":13,"price":18,"leves":[159,160,161,162,163,164,165,166,167,168,169,170,219,220,221,222,223,224,225,226,227,228,229,230],"ventures":[89],"drops":[21270000001671,1890000001836,16240000001598,13950000000629,23390000002275,1880000000275,1880000002008,19130000002005,1870000000278,36840000003350],"nodes":[158],"vendors":[1000999,1008837,1008838,1008839,1008840,1008841,1008842,1008843,1008844,1008845,1008846,1013117,1013118,1018662,1018663,1018664,1018665,1018666,1018667,1018668,1018669,1018670,1018671,1018672,1018673,1024548,1024549,1024550,1024551,1024552,1024553,1024554,1024555,1024556,1024557,1024558,1024559,1025039,1025043,1027015,1025717,1026169]}],"partials":[{"type":"item","id":"5306","obj":{"i":5306,"n":"Peiste Skin","l":38,"c":21822,"t":52}},{"type":"item","id":"5525","obj":{"i":5525,"n":"Black Alumen","l":37,"c":22604,"t":54}},{"type":"mob","id":"1740000000303","obj":{"i":1740000000303,"n":"Sandskin Peiste","l":"26 - 28","z":45}},{"type":"mob","id":"1730000000304","obj":{"i":1730000000304,"n":"Basilisk","l":"49","z":46}},{"type":"mob","id":"10470000001293","obj":{"i":10470000001293,"n":"Wyrmhound","l":"32","z":36}},{"type":"mob","id":"16170000001593","obj":{"i":16170000001593,"n":"Quicksand Basilisk","l":"38","z":47}},{"type":"mob","id":"21880000001993","obj":{"i":21880000001993,"n":"Rockskin Peiste","l":"28","z":45}},{"type":"mob","id":"28200000002586","obj":{"i":28200000002586,"n":"Pit Basilisk","l":"50","z":49}},{"type":"node","id":"49","obj":{"i":49,"n":"Urth's Gift","l":40,"t":0,"z":56}},{"type":"item","id":"5303","obj":{"i":5303,"n":"Boar Hide","l":33,"c":21816,"t":52}},{"type":"item","id":"5524","obj":{"i":5524,"n":"Alumen","l":17,"c":22616,"t":54}},{"type":"mob","id":"160000000015","obj":{"i":160000000015,"n":"Wild Hog","l":"45 - 46","z":56}},{"type":"mob","id":"31180000000015","obj":{"i":31180000000015,"n":"Wild Hog","l":"50","z":55}},{"type":"mob","id":"150000000016","obj":{"i":150000000016,"n":"Wild Boar","l":"18 - 21","z":55}},{"type":"mob","id":"21230000001667","obj":{"i":21230000001667,"n":"Phaia","l":"46","z":56}},{"type":"mob","id":"18860000001975","obj":{"i":18860000001975,"n":"Tusked Hog","l":"21","z":55}},{"type":"node","id":"160","obj":{"i":160,"n":"Drybone","l":20,"t":0,"z":44}},{"type":"npc","id":"1005554","obj":{"i":1005554,"n":"Amalj'aa Vendor","l":45,"s":2,"r":1,"a":482,"c":[23.28,14.17]}},{"type":"item","id":"21076","obj":{"i":21076,"n":"Steel Amalj'ok","l":1,"c":65050,"t":63}},{"type":"item","id":"5058","obj":{"i":5058,"n":"Steel Ingot","l":26,"c":20802,"t":49,"p":258}},{"type":"item","id":"5528","obj":{"i":5528,"n":"Bomb Ash","l":26,"c":21001,"t":54,"p":82}},{"type":"item","id":"5111","obj":{"i":5111,"n":"Iron Ore","l":13,"c":21202,"t":48,"p":18}},{"type":"node","id":"169","obj":{"i":169,"n":"Sagolii Desert","l":30,"t":1,"z":45}},{"type":"npc","id":"1008909","obj":{"i":1008909,"n":"Kobold Vendor","l":350,"s":2,"r":1,"a":944,"c":[21.65,17.83]}},{"type":"item","id":"21078","obj":{"i":21078,"n":"Titan Cobaltpiece","l":1,"c":"t/65052","t":63}},{"type":"mob","id":"170000000017","obj":{"i":170000000017,"n":"Balloon","l":"25 - 28","z":57}},{"type":"mob","id":"170000000132","obj":{"i":170000000132,"n":"Smoke Bomb","l":"32","z":45}},{"type":"mob","id":"170000000270","obj":{"i":170000000270,"n":"Grenade","l":"31","z":32}},{"type":"mob","id":"2570000000425","obj":{"i":2570000000425,"n":"Lady's Candle","l":"28","z":59}},{"type":"mob","id":"14150000001193","obj":{"i":14150000001193,"n":"Gas Bomb","l":"20","z":49}},{"type":"mob","id":"22660000002189","obj":{"i":22660000002189,"n":"Bright Balloon","l":"29","z":57}},{"type":"mob","id":"23440000002280","obj":{"i":23440000002280,"n":"Fulminator","l":"50","z":48}},{"type":"mob","id":"170000002688","obj":{"i":170000002688,"n":"Breeding Bomb","l":"41","z":350}},{"type":"mob","id":"170000002707","obj":{"i":170000002707,"n":"Glowing Bomb","l":"48","z":350}},{"type":"mob","id":"170000002743","obj":{"i":170000002743,"n":"Smart Bomb","l":"41","z":350}},{"type":"mob","id":"170000002745","obj":{"i":170000002745,"n":"Limpet Bomb","l":"41","z":350}},{"type":"node","id":"158","obj":{"i":158,"n":"Horizon's Edge","l":15,"t":0,"z":42}},{"type":"npc","id":"1000999","obj":{"i":1000999,"n":"Soemrwyb","l":28,"s":1,"t":"Guild Supplier","c":["10.6","15.1"]}},{"type":"npc","id":"1008837","obj":{"i":1008837,"n":"Material Supplier","s":3}},{"type":"npc","id":"1008838","obj":{"i":1008838,"n":"Material Supplier","s":3}},{"type":"npc","id":"1008839","obj":{"i":1008839,"n":"Material Supplier","s":3}},{"type":"npc","id":"1008840","obj":{"i":1008840,"n":"Material Supplier","s":3}},{"type":"npc","id":"1008841","obj":{"i":1008841,"n":"Material Supplier","s":3}},{"type":"npc","id":"1008842","obj":{"i":1008842,"n":"Material Supplier","s":3}},{"type":"npc","id":"1008843","obj":{"i":1008843,"n":"Material Supplier","s":3}},{"type":"npc","id":"1008844","obj":{"i":1008844,"n":"Material Supplier","s":3}},{"type":"npc","id":"1008845","obj":{"i":1008845,"n":"Material Supplier","s":3}},{"type":"npc","id":"1008846","obj":{"i":1008846,"n":"Material Supplier","s":3}},{"type":"npc","id":"1013117","obj":{"i":1013117,"n":"Material Supplier","s":3}},{"type":"npc","id":"1013118","obj":{"i":1013118,"n":"Material Supplier","s":3}},{"type":"npc","id":"1018662","obj":{"i":1018662,"n":"Material Supplier","s":3}},{"type":"npc","id":"1018663","obj":{"i":1018663,"n":"Material Supplier","s":3}},{"type":"npc","id":"1018664","obj":{"i":1018664,"n":"Material Supplier","s":3}},{"type":"npc","id":"1018665","obj":{"i":1018665,"n":"Material Supplier","s":3}},{"type":"npc","id":"1018666","obj":{"i":1018666,"n":"Material Supplier","s":3}},{"type":"npc","id":"1018667","obj":{"i":1018667,"n":"Material Supplier","s":3}},{"type":"npc","id":"1018668","obj":{"i":1018668,"n":"Material Supplier","s":3}},{"type":"npc","id":"1018669","obj":{"i":1018669,"n":"Material Supplier","s":3}},{"type":"npc","id":"1018670","obj":{"i":1018670,"n":"Material Supplier","s":3}},{"type":"npc","id":"1018671","obj":{"i":1018671,"n":"Material Supplier","s":3}},{"type":"npc","id":"1018672","obj":{"i":1018672,"n":"Material Supplier","s":3}},{"type":"npc","id":"1018673","obj":{"i":1018673,"n":"Material Supplier","s":3}},{"type":"npc","id":"1024548","obj":{"i":1024548,"n":"Material Supplier","s":3}},{"type":"npc","id":"1024549","obj":{"i":1024549,"n":"Material Supplier","s":3}},{"type":"npc","id":"1024550","obj":{"i":1024550,"n":"Material Supplier","s":3}},{"type":"npc","id":"1024551","obj":{"i":1024551,"n":"Material Supplier","s":3}},{"type":"npc","id":"1024552","obj":{"i":1024552,"n":"Material Supplier","s":3}},{"type":"npc","id":"1024553","obj":{"i":1024553,"n":"Material Supplier","s":3}},{"type":"npc","id":"1024554","obj":{"i":1024554,"n":"Material Supplier","s":3}},{"type":"npc","id":"1024555","obj":{"i":1024555,"n":"Material Supplier","s":3}},{"type":"npc","id":"1024556","obj":{"i":1024556,"n":"Material Supplier","s":3}},{"type":"npc","id":"1024557","obj":{"i":1024557,"n":"Material Supplier","s":3}},{"type":"npc","id":"1024558","obj":{"i":1024558,"n":"Material Supplier","s":3}},{"type":"npc","id":"1024559","obj":{"i":1024559,"n":"Material Supplier","s":3}},{"type":"npc","id":"1025039","obj":{"i":1025039,"n":"Allagan Resupply Node","s":3}},{"type":"npc","id":"1025043","obj":{"i":1025043,"n":"Ananta Material Supplier","s":3}},{"type":"npc","id":"1027015","obj":{"i":1027015,"n":"Kojin Material Supplier","s":3}},{"type":"npc","id":"1025717","obj":{"i":1025717,"n":"Namazu Material Supplier","s":3}},{"type":"npc","id":"1026169","obj":{"i":1026169,"n":"Namazu Material Supplier","s":3}},{"type":"mob","id":"1880000000275","obj":{"i":1880000000275,"n":"Quartz Doblyn","l":"49","z":46}},{"type":"mob","id":"1870000000278","obj":{"i":1870000000278,"n":"Lead Coblyn","l":"21","z":42}},{"type":"mob","id":"13950000000629","obj":{"i":13950000000629,"n":"Copperbell Coblyn","l":"17","z":48}},{"type":"mob","id":"16240000001598","obj":{"i":16240000001598,"n":"Schorl Doblyn","l":"38","z":47}},{"type":"mob","id":"21270000001671","obj":{"i":21270000001671,"n":"Asbestos Coblyn","l":"48","z":350}},{"type":"mob","id":"1890000001836","obj":{"i":1890000001836,"n":"Synthetic Doblyn","l":"48 - 49","z":350}},{"type":"mob","id":"19130000002005","obj":{"i":19130000002005,"n":"Ceruleum Coblyn","l":"38","z":46}},{"type":"mob","id":"1880000002008","obj":{"i":1880000002008,"n":"Sphene Doblyn","l":"49","z":46}},{"type":"mob","id":"23390000002275","obj":{"i":23390000002275,"n":"Chalcopyrite Coblyn","l":"50","z":48}},{"type":"mob","id":"36840000003350","obj":{"i":36840000003350,"n":"Cermet Coblyn","l":"50","z":418}},{"type":"item","id":"1132","obj":{"i":1132,"n":"Weathered Fingerless Gloves","l":1,"c":"t/44064","t":37}},{"type":"item","id":"3519","obj":{"i":3519,"n":"Asuran Armguards","l":11,"c":44070,"t":37}},{"type":"item","id":"3530","obj":{"i":3530,"n":"Fingerless Leather Gloves","l":5,"c":44060,"t":37,"p":126}},{"type":"item","id":"3546","obj":{"i":3546,"n":"Fingerless Hard Leather Gloves","l":15,"c":44061,"t":37,"p":420}},{"type":"item","id":"3576","obj":{"i":3576,"n":"Fingerless Goatskin Gloves","l":25,"c":44062,"t":37,"p":1282}},{"type":"item","id":"3578","obj":{"i":3578,"n":"Fingerless Goatskin Gloves of Gathering","l":25,"c":44062,"t":37,"p":1282}},{"type":"item","id":"3584","obj":{"i":3584,"n":"Brigand's Gloves","l":26,"c":44074,"t":37}},{"type":"item","id":"3611","obj":{"i":3611,"n":"Fingerless Boarskin Gloves","l":35,"c":44101,"t":37,"p":3024}},{"type":"item","id":"3613","obj":{"i":3613,"n":"Fingerless Boarskin Gloves of Gathering","l":35,"c":44101,"t":37,"p":3024}},{"type":"item","id":"3627","obj":{"i":3627,"n":"Fingerless Peisteskin Gloves of Gathering","l":40,"c":44102,"t":37,"p":3780}},{"type":"item","id":"3651","obj":{"i":3651,"n":"Fingerless Raptorskin Gloves","l":45,"c":44103,"t":37,"p":4620}},{"type":"item","id":"3653","obj":{"i":3653,"n":"Fingerless Raptorskin Gloves of Gathering","l":45,"c":44103,"t":37,"p":4620}},{"type":"item","id":"3673","obj":{"i":3673,"n":"Sipahi Gloves","l":55,"c":44075,"t":37}},{"type":"item","id":"31538","obj":{"i":31538,"n":"Buccaneer's Gloves","l":46,"c":44075,"t":37}},{"type":"npc","id":"1006800","obj":{"i":1006800,"n":"Merchant & Mender","l":63,"s":5,"a":402,"c":[13.28,15.97]}},{"type":"npc","id":"1000215","obj":{"i":1000215,"n":"Domitien","l":53,"s":15,"t":"Independent Tailor","c":["14.3","9.8"]}},{"type":"npc","id":"1001203","obj":{"i":1001203,"n":"Iron Thunder","l":29,"s":15,"q":1,"t":"Battlecraft Supplier","a":744,"c":[8.11,11.67]}},{"type":"npc","id":"1001965","obj":{"i":1001965,"n":"Gwalter","l":41,"s":15,"t":"Battlecraft Armorer","c":["13.6","10.0"]}},{"type":"npc","id":"1011204","obj":{"i":1011204,"n":"Norlaise","l":2301,"s":19,"q":1,"t":"Armorer","a":2317,"c":[7.17,10.18]}},{"type":"item","id":"5284","obj":{"i":5284,"n":"Peiste Leather","l":38,"c":22024,"t":52}},{"type":"item","id":"5282","obj":{"i":5282,"n":"Boar Leather","l":33,"c":22015,"t":52}},{"type":"item","id":"5093","obj":{"i":5093,"n":"Steel Rivets","l":27,"c":21003,"t":49,"p":313}},{"type":"quest","id":"66492","obj":{"i":66492,"n":"With the Utmost Care","g":1,"l":"Eastern Thanalan","s":215}},{"type":"leve","id":"127","obj":{"i":127,"n":"Through a Glass Brightly","l":35,"j":13,"p":385}},{"type":"leve","id":"643","obj":{"i":643,"n":"Subduing the Subprime","l":40,"j":34,"p":325}},{"type":"leve","id":"644","obj":{"i":644,"n":"Necrologos: Pale Oblation","l":40,"j":34,"p":325}},{"type":"leve","id":"645","obj":{"i":645,"n":"Don't Forget to Cry","l":40,"j":34,"p":325}},{"type":"leve","id":"646","obj":{"i":646,"n":"Circling the Ceruleum","l":40,"j":34,"p":325}},{"type":"leve","id":"647","obj":{"i":647,"n":"Someone's in the Doghouse","l":40,"j":34,"p":325}},{"type":"leve","id":"648","obj":{"i":648,"n":"Blow-up Incubator","l":40,"j":34,"p":325}},{"type":"leve","id":"649","obj":{"i":649,"n":"Necrologos: Whispers of the Gem","l":40,"j":34,"p":402}},{"type":"leve","id":"650","obj":{"i":650,"n":"Got a Gut Feeling about This","l":40,"j":34,"p":402}},{"type":"leve","id":"651","obj":{"i":651,"n":"You Look Good Enough to Eat","l":40,"j":34,"p":402}},{"type":"leve","id":"652","obj":{"i":652,"n":"The Area's a Bit Sketchy","l":40,"j":34,"p":402}},{"type":"leve","id":"653","obj":{"i":653,"n":"The Tropes of the Trade","l":40,"j":34,"p":402}},{"type":"leve","id":"654","obj":{"i":654,"n":"Pets Are Family Too","l":40,"j":34,"p":402}},{"type":"leve","id":"655","obj":{"i":655,"n":"We Can Dismember It for You Wholesale","l":40,"j":34,"p":402}},{"type":"item","id":"3630","obj":{"i":3630,"n":"Serpent Sergeant's Bracers","l":40,"c":44119,"t":37}},{"type":"item","id":"3645","obj":{"i":3645,"n":"Woolen Bracers","l":43,"c":44099,"t":37}},{"type":"item","id":"3619","obj":{"i":3619,"n":"Steel Mitt Gauntlets","l":37,"c":44531,"t":37,"p":3978}},{"type":"item","id":"3642","obj":{"i":3642,"n":"Mythril Mitt Gauntlets","l":42,"c":44534,"t":37}},{"type":"npc","id":"1002385","obj":{"i":1002385,"n":"Vivenne","l":63}},{"type":"item","id":"3964","obj":{"i":3964,"n":"Frayed Chef's Belt","l":32,"c":47251,"t":39,"p":932}},{"type":"item","id":"3602","obj":{"i":3602,"n":"Blackened Smithy's Gloves","l":34,"c":44072,"t":37,"p":1440}},{"type":"item","id":"3830","obj":{"i":3830,"n":"Mildewed Thighboots","l":36,"c":46179,"t":38,"p":1809}},{"type":"item","id":"3625","obj":{"i":3625,"n":"Fingerless Peisteskin Gloves","l":40,"c":44102,"t":37,"p":3780}}]}