{"leve":{"name":"Get Me to the War on Time","description":"Since the loss of the Stone Vigil, the armory at the Whitebrim outpost is swathed in a veil of sparks, ever renewed by hammers that fall night and day. What vengeful bride do the smiths attend, in that harsh and clangorous place that wears down metal and men alike?","id":193,"patch":2.0,"client":"Independent Sutler, Lanquairt the Lean","lvl":40,"jobCategory":10,"levemete":1002402,"areaid":402,"xp":138260,"gil":403,"rewards":39,"plate":80033,"frame":80005,"areaicon":110063,"requires":[{"item":2376}],"complexity":{"nq":5,"hq":273}},"rewards":{"id":39,"entries":[{"item":2,"rate":0.27,"amount":34},{"item":5,"rate":0.27,"amount":34},{"item":5114,"rate":0.27,"amount":15},{"item":2,"rate":0.04,"amount":56},{"item":5,"rate":0.04,"amount":56},{"item":1613,"rate":0.04},{"item":1621,"rate":0.04},{"item":1771,"rate":0.04}]},"ingredients":[{"name":"Cobalt Doming Hammer","id":2376,"icon":35207,"category":16,"ilvl":43,"price":5859,"craft":[{"id":1193,"job":9,"rlvl":43,"durability":80,"quality":2251,"progress":155,"lvl":43,"suggestedCraftsmanship":150,"suggestedControl":75,"materialQualityFactor":50,"hq":1,"quickSynth":1,"ingredients":[{"id":5059,"amount":1,"quality":399.971069},{"id":5373,"amount":1,"quality":306.954559},{"id":5094,"amount":1,"quality":418.574371},{"id":2,"amount":5},{"id":5,"amount":5}],"complexity":{"nq":253,"hq":273}}],"vendors":[1006898,1006952,1005180,1005181,1004598,1004160,1000218,1001973,1003254,1011206]},{"name":"Cobalt Ingot","id":5059,"icon":20802,"category":49,"ilvl":43,"price":763,"craft":[{"id":153,"job":9,"rlvl":42,"durability":40,"quality":2147,"progress":72,"lvl":42,"suggestedCraftsmanship":150,"suggestedControl":75,"materialQualityFactor":50,"hq":1,"quickSynth":1,"ingredients":[{"id":5116,"amount":2,"quality":466.26767},{"id":5111,"amount":1,"quality":140.964645},{"id":2,"amount":5}],"complexity":{"nq":69,"hq":89}},{"id":273,"job":10,"rlvl":42,"durability":40,"quality":2147,"progress":72,"lvl":42,"suggestedCraftsmanship":150,"suggestedControl":75,"materialQualityFactor":50,"hq":1,"quickSynth":1,"ingredients":[{"id":5116,"amount":2,"quality":466.26767},{"id":5111,"amount":1,"quality":140.964645},{"id":3,"amount":5}],"complexity":{"nq":69,"hq":89}}]},{"name":"Cobalt Ore","id":5116,"icon":21216,"category":48,"ilvl":43,"price":228,"tradeShops":[{"shop":"Curious Crop Exchange","npcs":[1005633,1005640,1005647,1018091,1018094,1018097,1019101,1019111],"listings":[{"item":[{"id":"5116","amount":6}],"currency":[{"id":"15858","amount":1}]}]}],"leves":[195,196,197,198,199,200,255,256,257,258,259,260],"ventures":[157],"nodes":[189]},{"name":"Iron Ore","id":5111,"icon":21202,"category":48,"ilvl":13,"price":18,"leves":[159,160,161,162,163,164,165,166,167,168,169,170,219,220,221,222,223,224,225,226,227,228,229,230],"ventures":[89],"drops":[21270000001671,1890000001836,16240000001598,13950000000629,23390000002275,1880000000275,1880000002008,19130000002005,1870000000278,36840000003350],"nodes":[158],"vendors":[1000999,1008837,1008838,1008839,1008840,1008841,1008842,1008843,1008844,1008845,1008846,1013117,1013118,1018662,1018663,1018664,1018665,1018666,1018667,1018668,1018669,1018670,1018671,1018672,1018673,1024548,1024549,1024550,1024551,1024552,1024553,1024554,1024555,1024556,1024557,1024558,1024559,1025039,1025043,1027015,1025717,1026169]},{"name":"Oak Lumber","id":5373,"icon":22455,"category":50,"ilvl":33,"price":470,"craft":[{"id":1069,"job":8,"rlvl":32,"durability":40,"quality":1697,"progress":55,"lvl":32,"suggestedCraftsmanship":121,"suggestedControl":60,"materialQualityFactor":50,"hq":1,"quickSynth":1,"ingredients":[{"id":5390,"amount":3,"quality":282.833344},{"id":4,"amount":3}],"complexity":{"nq":64,"hq":84}}],"vendors":[1009205]},{"name":"Oak Log","id":5390,"icon":22401,"category":50,"ilvl":32,"price":130,"leves":[57,58,59,60,61,62,63,64,65,66,67,68],"ventures":[269],"nodes":[28]},{"name":"Cobalt Rivets","id":5094,"icon":21003,"category":49,"ilvl":45,"price":891,"craft":[{"id":155,"job":9,"rlvl":43,"durability":40,"quality":2251,"progress":77,"lvl":43,"suggestedCraftsmanship":150,"suggestedControl":75,"materialQualityFactor":50,"hq":1,"quickSynth":1,"ingredients":[{"id":5059,"amount":1,"quality":1125.5},{"id":2,"amount":5}],"complexity":{"nq":109,"hq":129}},{"id":282,"job":10,"rlvl":44,"durability":40,"quality":2277,"progress":78,"lvl":44,"suggestedCraftsmanship":150,"suggestedControl":75,"materialQualityFactor":50,"hq":1,"quickSynth":1,"ingredients":[{"id":5059,"amount":1,"quality":1138.5},{"id":3,"amount":5}],"complexity":{"nq":109,"hq":129}}]}],"partials":[{"type":"item","id":"5116","obj":{"i":5116,"n":"Cobalt Ore","l":43,"c":21216,"t":48}},{"type":"item","id":"5111","obj":{"i":5111,"n":"Iron Ore","l":13,"c":21202,"t":48,"p":18}},{"type":"node","id":"189","obj":{"i":189,"n":"Bluefog","l":50,"t":0,"z":46}},{"type":"npc","id":"1005633","obj":{"i":1005633,"n":"Material Supplier","l":425,"s":3,"r":1,"a":1202,"c":[11.04,11.4]}},{"type":"npc","id":"1005640","obj":{"i":1005640,"n":"Material Supplier","l":427,"s":3,"r":1,"a":1115,"c":[10.97,8.96]}},{"type":"npc","id":"1005647","obj":{"i":1005647,"n":"Material Supplier","l":426,"s":3,"r":1,"a":1146,"c":[11.94,8.33]}},{"type":"npc","id":"1018091","obj":{"i":1018091,"n":"Apartment Merchant","l":1813,"s":8,"r":1,"a":1146,"c":[6.15,6.03]}},{"type":"npc","id":"1018094","obj":{"i":1018094,"n":"Apartment Merchant","l":1811,"s":8,"r":1,"a":1146,"c":[6.15,6.03]}},{"type":"npc","id":"1018097","obj":{"i":1018097,"n":"Apartment Merchant","l":1815,"s":8,"r":1,"a":1146,"c":[6.15,6.03]}},{"type":"npc","id":"1019101","obj":{"i":1019101,"n":"Material Supplier","l":2412,"s":3,"r":1,"c":["10.5","12.2"]}},{"type":"npc","id":"1019111","obj":{"i":1019111,"n":"Apartment Merchant","l":2272,"s":8,"r":1,"c":["6.1","6.0"]}},{"type":"item","id":"15858","obj":{"i":15858,"n":"Voidrake","l":155,"c":25004,"t":54}},{"type":"node","id":"158","obj":{"i":158,"n":"Horizon's Edge","l":15,"t":0,"z":42}},{"type":"npc","id":"1000999","obj":{"i":1000999,"n":"Soemrwyb","l":28,"s":1,"t":"Guild Supplier","c":["10.6","15.1"]}},{"type":"npc","id":"1008837","obj":{"i":1008837,"n":"Material Supplier","s":3}},{"type":"npc","id":"1008838","obj":{"i":1008838,"n":"Material Supplier","s":3}},{"type":"npc","id":"1008839","obj":{"i":1008839,"n":"Material Supplier","s":3}},{"type":"npc","id":"1008840","obj":{"i":1008840,"n":"Material Supplier","s":3}},{"type":"npc","id":"1008841","obj":{"i":1008841,"n":"Material Supplier","s":3}},{"type":"npc","id":"1008842","obj":{"i":1008842,"n":"Material Supplier","s":3}},{"type":"npc","id":"1008843","obj":{"i":1008843,"n":"Material Supplier","s":3}},{"type":"npc","id":"1008844","obj":{"i":1008844,"n":"Material Supplier","s":3}},{"type":"npc","id":"1008845","obj":{"i":1008845,"n":"Material Supplier","s":3}},{"type":"npc","id":"1008846","obj":{"i":1008846,"n":"Material Supplier","s":3}},{"type":"npc","id":"1013117","obj":{"i":1013117,"n":"Material Supplier","s":3}},{"type":"npc","id":"1013118","obj":{"i":1013118,"n":"Material Supplier","s":3}},{"type":"npc","id":"1018662","obj":{"i":1018662,"n":"Material Supplier","s":3}},{"type":"npc","id":"1018663","obj":{"i":1018663,"n":"Material Supplier","s":3}},{"type":"npc","id":"1018664","obj":{"i":1018664,"n":"Material Supplier","s":3}},{"type":"npc","id":"1018665","obj":{"i":1018665,"n":"Material Supplier","s":3}},{"type":"npc","id":"1018666","obj":{"i":1018666,"n":"Material Supplier","s":3}},{"type":"npc","id":"1018667","obj":{"i":1018667,"n":"Material Supplier","s":3}},{"type":"npc","id":"1018668","obj":{"i":1018668,"n":"Material Supplier","s":3}},{"type":"npc","id":"1018669","obj":{"i":1018669,"n":"Material Supplier","s":3}},{"type":"npc","id":"1018670","obj":{"i":1018670,"n":"Material Supplier","s":3}},{"type":"npc","id":"1018671","obj":{"i":1018671,"n":"Material Supplier","s":3}},{"type":"npc","id":"1018672","obj":{"i":1018672,"n":"Material Supplier","s":3}},{"type":"npc","id":"1018673","obj":{"i":1018673,"n":"Material Supplier","s":3}},{"type":"npc","id":"1024548","obj":{"i":1024548,"n":"Material Supplier","s":3}},{"type":"npc","id":"1024549","obj":{"i":1024549,"n":"Material Supplier","s":3}},{"type":"npc","id":"1024550","obj":{"i":1024550,"n":"Material Supplier","s":3}},{"type":"npc","id":"1024551","obj":{"i":1024551,"n":"Material Supplier","s":3}},{"type":"npc","id":"1024552","obj":{"i":1024552,"n":"Material Supplier","s":3}},{"type":"npc","id":"1024553","obj":{"i":1024553,"n":"Material Supplier","s":3}},{"type":"npc","id":"1024554","obj":{"i":1024554,"n":"Material Supplier","s":3}},{"type":"npc","id":"1024555","obj":{"i":1024555,"n":"Material Supplier","s":3}},{"type":"npc","id":"1024556","obj":{"i":1024556,"n":"Material Supplier","s":3}},{"type":"npc","id":"1024557","obj":{"i":1024557,"n":"Material Supplier","s":3}},{"type":"npc","id":"1024558","obj":{"i":1024558,"n":"Material Supplier","s":3}},{"type":"npc","id":"1024559","obj":{"i":1024559,"n":"Material Supplier","s":3}},{"type":"npc","id":"1025039","obj":{"i":1025039,"n":"Allagan Resupply Node","s":3}},{"type":"npc","id":"1025043","obj":{"i":1025043,"n":"Ananta Material Supplier","s":3}},{"type":"npc","id":"1027015","obj":{"i":1027015,"n":"Kojin Material Supplier","s":3}},{"type":"npc","id":"1025717","obj":{"i":1025717,"n":"Namazu Material Supplier","s":3}},{"type":"npc","id":"1026169","obj":{"i":1026169,"n":"Namazu Material Supplier","s":3}},{"type":"mob","id":"1880000000275","obj":{"i":1880000000275,"n":"Quartz Doblyn","l":"49","z":46}},{"type":"mob","id":"1870000000278","obj":{"i":1870000000278,"n":"Lead Coblyn","l":"21","z":42}},{"type":"mob","id":"13950000000629","obj":{"i":13950000000629,"n":"Copperbell Coblyn","l":"17","z":48}},{"type":"mob","id":"16240000001598","obj":{"i":16240000001598,"n":"Schorl Doblyn","l":"38","z":47}},{"type":"mob","id":"21270000001671","obj":{"i":21270000001671,"n":"Asbestos Coblyn","l":"48","z":350}},{"type":"mob","id":"1890000001836","obj":{"i":1890000001836,"n":"Synthetic Doblyn","l":"48 - 49","z":350}},{"type":"mob","id":"19130000002005","obj":{"i":19130000002005,"n":"Ceruleum Coblyn","l":"38","z":46}},{"type":"mob","id":"1880000002008","obj":{"i":1880000002008,"n":"Sphene Doblyn","l":"49","z":46}},{"type":"mob","id":"23390000002275","obj":{"i":23390000002275,"n":"Chalcopyrite Coblyn","l":"50","z":48}},{"type":"mob","id":"36840000003350","obj":{"i":36840000003350,"n":"Cermet Coblyn","l":"50","z":418}},{"type":"npc","id":"1009205","obj":{"i":1009205,"n":"Ixali Vendor","l":57,"s":3,"r":1,"c":["24.9","22.7"]}},{"type":"item","id":"5390","obj":{"i":5390,"n":"Oak Log","l":32,"c":22401,"t":50}},{"type":"node","id":"28","obj":{"i":28,"n":"Lower Paths","l":35,"t":2,"z":56}},{"type":"item","id":"5059","obj":{"i":5059,"n":"Cobalt Ingot","l":43,"c":20802,"t":49}},{"type":"item","id":"2366","obj":{"i":2366,"n":"Weathered Doming Hammer","l":1,"c":35203,"t":16,"p":72}},{"type":"item","id":"2367","obj":{"i":2367,"n":"Bronze Doming Hammer","l":8,"c":35201,"t":16,"p":268}},{"type":"item","id":"2368","obj":{"i":2368,"n":"Amateur's Doming Hammer","l":11,"c":35201,"t":16,"p":384}},{"type":"item","id":"2370","obj":{"i":2370,"n":"Iron Doming Hammer","l":18,"c":35202,"t":16,"p":741}},{"type":"item","id":"2371","obj":{"i":2371,"n":"Initiate's Doming Hammer","l":21,"c":35202,"t":16,"p":1009}},{"type":"item","id":"2374","obj":{"i":2374,"n":"Steel Doming Hammer","l":34,"c":35207,"t":16,"p":3951}},{"type":"item","id":"19508","obj":{"i":19508,"n":"High Steel Doming Hammer","l":190,"c":35221,"t":16,"p":27086}},{"type":"npc","id":"1006898","obj":{"i":1006898,"n":"Merchant & Mender","l":67,"s":5,"c":["30.0","12.4"]}},{"type":"npc","id":"1006952","obj":{"i":1006952,"n":"Independent Merchant","l":67,"s":5,"c":["21.8","6.9"]}},{"type":"npc","id":"1005180","obj":{"i":1005180,"n":"Merchant & Mender","l":33,"s":5,"a":226,"c":[21.89,20.22]}},{"type":"npc","id":"1005181","obj":{"i":1005181,"n":"Merchant & Mender","l":33,"s":5,"a":227,"c":[19.68,23.18]}},{"type":"npc","id":"1004598","obj":{"i":1004598,"n":"Merchant & Mender","l":46,"s":5,"c":["21.4","22.1"]}},{"type":"npc","id":"1004160","obj":{"i":1004160,"n":"Merchant & Mender","l":46,"s":5,"c":["20.8","30.9"]}},{"type":"npc","id":"1000218","obj":{"i":1000218,"n":"Admiranda","l":53,"s":11,"q":1,"t":"Tool Supplier","a":565,"c":[14.55,10.09]}},{"type":"npc","id":"1001973","obj":{"i":1001973,"n":"Yoyobasa","l":41,"s":11,"t":"Fieldcraft Merchant","c":["14.2","11.2"]}},{"type":"npc","id":"1003254","obj":{"i":1003254,"n":"Syneyhil","l":29,"s":11,"q":1,"t":"Fieldcraft Supplier","a":745,"c":[6.31,11.99]}},{"type":"npc","id":"1011206","obj":{"i":1011206,"n":"Evrardoux","l":2301,"s":7,"t":"Fieldcraft Supplier","a":2317,"c":[6.51,9.6]}},{"type":"item","id":"5373","obj":{"i":5373,"n":"Oak Lumber","l":33,"c":22455,"t":50,"p":470}},{"type":"item","id":"5094","obj":{"i":5094,"n":"Cobalt Rivets","l":45,"c":21003,"t":49}},{"type":"quest","id":"65819","obj":{"i":65819,"n":"For the Good of the Guild","g":110,"l":"Limsa Lominsa","s":450,"f":1}},{"type":"leve","id":"193","obj":{"i":193,"n":"Get Me to the War on Time","l":40,"j":10,"p":402}},{"type":"item","id":"2375","obj":{"i":2375,"n":"Steel Raising Hammer","l":38,"c":35058,"t":16,"p":4753}},{"type":"item","id":"2377","obj":{"i":2377,"n":"Cobalt Raising Hammer","l":48,"c":35208,"t":16,"p":7080}},{"type":"npc","id":"1002402","obj":{"i":1002402,"n":"Lanquairt","l":63}},{"type":"item","id":"5114","obj":{"i":5114,"n":"Mythril Ore","l":34,"c":21208,"t":48}},{"type":"item","id":"1613","obj":{"i":1613,"n":"Blunt Goblin Scimitar","l":37,"c":30425,"t":2,"p":2273}},{"type":"item","id":"1621","obj":{"i":1621,"n":"Blunt Goblin Longsword","l":40,"c":30428,"t":2,"p":2862}},{"type":"item","id":"1771","obj":{"i":1771,"n":"Notched Bill","l":42,"c":31417,"t":3,"p":4222}},{"type":"item","id":"2376","obj":{"i":2376,"n":"Cobalt Doming Hammer","l":43,"c":35207,"t":16,"p":5859}}]}